setup.py
zoran_tools/__init__.py
zoran_tools/common.py
zoran_tools/csv_tools.py
zoran_tools/csvdb.py
zoran_tools/db_tools.py
zoran_tools/json_tools.py
zoran_tools/log.py
zoran_tools/path_tools.py
zoran_tools/udf_funcs.py
zoran_tools/zoran_tools.py
zoran_tools.egg-info/PKG-INFO
zoran_tools.egg-info/SOURCES.txt
zoran_tools.egg-info/dependency_links.txt
zoran_tools.egg-info/top_level.txt
zoran_tools/calculate/__init__.py
zoran_tools/calculate/barrier.py
zoran_tools/calculate/calculations.py
zoran_tools/frame/__init__.py
zoran_tools/frame/frame/__init__.py
zoran_tools/frame/frame/creator.py
zoran_tools/frame/frame/exception.py
zoran_tools/frame/frame/sql.py
zoran_tools/frame/tools/__init__.py
zoran_tools/frame/tools/prettytable.py