Metadata-Version: 1.0
Name: zoran-tools
Version: 0.2.2
Summary: 自用的一些小工具,包括列出文件夹下的文件, 读写CSV等
Home-page: UNKNOWN
Author: bkiu
Author-email: chenzhongrun@bonc.com.cn
License: UNKNOWN
Platform: UNKNOWN
